company_house_clients/__init__.py
company_house_clients/base_client.py
company_house_clients/company_house/__init__.py
company_house_clients/company_house/rest.py
company_house_clients/company_house/streaming.py
companies_shared_clients-0.1.3.dist-info/METADATA
companies_shared_clients-0.1.3.dist-info/WHEEL
companies_shared_clients-0.1.3.dist-info/top_level.txt
companies_shared_clients-0.1.3.dist-info/RECORD
