Metadata-Version: 2.1
Name: companies-shared-clients
Version: 0.1.3
Summary: Shared Clients
Home-page: https://github.com/companiesinfo/companies-shared-clients
Author: Bakhodir Ramazonov
Author-email: boxa.devops@gmail.com
Classifier: Programming Language :: Python :: 3
Classifier: License :: OSI Approved :: MIT License
Classifier: Operating System :: OS Independent
Requires-Python: >=3.6
